[
  {
    "rootID": "20241119104212-0zvwp1v",
    "icon": "",
    "title": "着色器关键字 - Unity 手册"
  },
  {
    "rootID": "20241119103639-shzdnl6",
    "icon": "",
    "title": "着色器中的条件语句 - Unity 手册"
  },
  {
    "rootID": "20241119102740-h0my8wk",
    "icon": "",
    "title": "在 HLSL 中声明和使用着色器关键字 - Unity 手册"
  },
  {
    "rootID": "20241118130527-dc8vhbh",
    "icon": "",
    "title": "HLSL中的pragma指令 - Unity 手册"
  },
  {
    "rootID": "20241114173715-it590ps",
    "icon": "",
    "title": "内置着色器变量"
  },
  {
    "rootID": "20241119103015-t8x0ztl",
    "icon": "",
    "title": "HLSL中的目标着色器模型和GPU功能 - Unity 手册"
  },
  {
    "rootID": "20241114173849-h3dzc0y",
    "icon": "",
    "title": "设计模式UML"
  },
  {
    "rootID": "20241114182725-u4c9t76",
    "icon": "2721-fe0f",
    "title": "数据驱动类技能 - Valve Developer Community"
  },
  {
    "rootID": "20241114181116-jgpv9jm",
    "icon": "",
    "title": "未命名"
  }
]